odoo10_addon_contract_show_invoice-10.0.1.0.2-nspkg.pth
odoo/addons/contract_show_invoice/README.rst
odoo/addons/contract_show_invoice/__init__.py
odoo/addons/contract_show_invoice/__manifest__.py
odoo/addons/contract_show_invoice/i18n/contract_show_invoice.pot
odoo/addons/contract_show_invoice/i18n/de.po
odoo/addons/contract_show_invoice/i18n/es.po
odoo/addons/contract_show_invoice/i18n/fi.po
odoo/addons/contract_show_invoice/i18n/fr.po
odoo/addons/contract_show_invoice/i18n/hi_IN.po
odoo/addons/contract_show_invoice/i18n/hr.po
odoo/addons/contract_show_invoice/i18n/hr_HR.po
odoo/addons/contract_show_invoice/i18n/it.po
odoo/addons/contract_show_invoice/i18n/nl.po
odoo/addons/contract_show_invoice/i18n/nl_NL.po
odoo/addons/contract_show_invoice/i18n/pt.po
odoo/addons/contract_show_invoice/i18n/pt_BR.po
odoo/addons/contract_show_invoice/i18n/ro.po
odoo/addons/contract_show_invoice/i18n/ru.po
odoo/addons/contract_show_invoice/i18n/tr.po
odoo/addons/contract_show_invoice/i18n/tr_TR.po
odoo/addons/contract_show_invoice/models/__init__.py
odoo/addons/contract_show_invoice/models/account_analytic_account.py
odoo/addons/contract_show_invoice/models/invoice.py
odoo/addons/contract_show_invoice/static/description/icon.png
odoo/addons/contract_show_invoice/tests/__init__.py
odoo/addons/contract_show_invoice/tests/test_contract_show_invoice.py
odoo/addons/contract_show_invoice/views/contract_view.xml
odoo10_addon_contract_show_invoice-10.0.1.0.2.dist-info/METADATA
odoo10_addon_contract_show_invoice-10.0.1.0.2.dist-info/WHEEL
odoo10_addon_contract_show_invoice-10.0.1.0.2.dist-info/namespace_packages.txt
odoo10_addon_contract_show_invoice-10.0.1.0.2.dist-info/top_level.txt
odoo10_addon_contract_show_invoice-10.0.1.0.2.dist-info/RECORD
