Metadata-Version: 2.1
Name: odoo10-addon-contract-show-invoice
Version: 10.0.1.0.2
Summary: Button in contracts to show their invoices
Home-page: http://www.domatix.com
Author: Domatix,Tecnativa,Odoo Community Association (OCA)
Author-email: support@odoo-community.org
License: AGPL-3
Platform: UNKNOWN
Classifier: Programming Language :: Python
Classifier: Framework :: Odoo
Classifier: License :: OSI Approved :: GNU Affero General Public License v3
Requires-Python: ~=2.7
Requires-Dist: odoo (<10.1dev,>=10.0)
